Workbook

Sheet Dashboard
A1: Online Payroll System (OPS) – Development Tracker (target finish Nov 30, 2026)
A2: ="Project Owner: "&Tracker!C3&" | "&TEXT(Tracker!C4,"mmm d, yyyy")&" to "&TEXT(Tracker!C4+11*7-1,"mmm d, yyyy")&" | 11 weeks, "&COUNTA(Tracker!A9:A31)&" tasks" -> Project Owner: Thea Consignado | Sep 15, 2026 to Nov 30, 2026 | 11 weeks, 23 tasks
A4: OVERALL PROGRESS | C4: PLANNED BY END OF THIS WEEK | E4: AGAINST PLAN (POINTS) | G4: TASKS DONE
A5: =Tracker!J32 -> 0.45549738 | C5: =Tracker!K32 -> 0.29842932 | E5: =Tracker!L32 -> 15.706806 | G5: =COUNTIF(Tracker!I9:I31,"Done")&" / "&COUNTA(Tracker!A9:A31) -> 1 / 23
A6: ="Weighted by effort days" -> Weighted by effort days | C6: =IF(Tracker!C6=0,"Project has not started","Week "&Tracker!C6&" of 11") -> Week 3 of 11 | E6: =IF(ABS(Tracker!L32)<=2,"On plan",IF(Tracker!L32>0,"Ahead of plan","Behind plan")) -> Ahead of plan | G6: =IF(Tracker!C6=0,"11 weeks to go",IF(11-Tracker!C6=0,"Final week",11-Tracker!C6&" weeks left")) -> 8 weeks left
A9: Progress by work stream | F9: Task status
A10: Work stream | B10: Effort (days) | C10: Actual % | D10: Planned % | F10: Status | G10: Tasks
A11: Foundation | B11: =SUMIFS(Tracker!$F$9:$F$31,Tracker!$B$9:$B$31,A11) -> 37 | C11: =SUMPRODUCT((Tracker!$B$9:$B$31=A11)*Tracker!$F$9:$F$31*Tracker!$J$9:$J$31)/B11 -> 0.56756757 | D11: =SUMPRODUCT((Tracker!$B$9:$B$31=A11)*Tracker!$F$9:$F$31*Tracker!$K$9:$K$31)/B11 -> 1 | F11: Done | G11: =COUNTIF(Tracker!$I$9:$I$31,F11) -> 1
A12: Workforce and time | B12: =SUMIFS(Tracker!$F$9:$F$31,Tracker!$B$9:$B$31,A12) -> 50 | C12: =SUMPRODUCT((Tracker!$B$9:$B$31=A12)*Tracker!$F$9:$F$31*Tracker!$J$9:$J$31)/B12 -> 0.5 | D12: =SUMPRODUCT((Tracker!$B$9:$B$31=A12)*Tracker!$F$9:$F$31*Tracker!$K$9:$K$31)/B12 -> 0.4 | F12: In progress | G12: =COUNTIF(Tracker!$I$9:$I$31,F12) -> 20
A13: Payroll and compliance | B13: =SUMIFS(Tracker!$F$9:$F$31,Tracker!$B$9:$B$31,A13) -> 56 | C13: =SUMPRODUCT((Tracker!$B$9:$B$31=A13)*Tracker!$F$9:$F$31*Tracker!$J$9:$J$31)/B13 -> 0.5 | D13: =SUMPRODUCT((Tracker!$B$9:$B$31=A13)*Tracker!$F$9:$F$31*Tracker!$K$9:$K$31)/B13 -> 0 | F13: In testing | G13: =COUNTIF(Tracker!$I$9:$I$31,F13) -> 0
A14: Portals, platform and launch | B14: =SUMIFS(Tracker!$F$9:$F$31,Tracker!$B$9:$B$31,A14) -> 48 | C14: =SUMPRODUCT((Tracker!$B$9:$B$31=A14)*Tracker!$F$9:$F$31*Tracker!$J$9:$J$31)/B14 -> 0.27083333 | D14: =SUMPRODUCT((Tracker!$B$9:$B$31=A14)*Tracker!$F$9:$F$31*Tracker!$K$9:$K$31)/B14 -> 0 | F14: Not started | G14: =COUNTIF(Tracker!$I$9:$I$31,F14) -> 2
A15: All streams | B15: =SUM(B11:B14) -> 191 | C15: =Tracker!J32 -> 0.45549738 | D15: =Tracker!K32 -> 0.29842932 | F15: Behind plan | G15: =COUNTIF(Tracker!$M$9:$M$31,"Behind plan") -> 6
F16: Total tasks | G16: =SUM(G11:G14) -> 23
A58: Charts update when you change Status on the Tracker sheet and enter Actual % on the Weekly sheet.

Sheet Tracker
A1: Inventory System – 3-Month Development Tracker
A2: ="Project Owner: "&C3&" | Tasks, schedule, and progress for the 11-week build, target finish Nov 30, 2026" -> Project Owner: Thea Consignado | Tasks, schedule, and progress for the 11-week build, target finish Nov 30, 2026
A3: Project owner | C3: Thea Consignado | E3: HOW TO USE
A4: Project start date | C4: 46280 | E4: 1. Set the project owner and start date (C3, C4). Week 1 starts 15 Sep 2026; week 11 ends 30 Nov 2026 (target finish).
A5: Report date (default = today) | C5: =TODAY() -> 46300 | E5: 2. Pick a Status for each task in column I. Progress % is calculated from it (set what each status counts as on the Lists sheet).
A6: Current week (0 = not started) | C6: =MAX(0,MIN(11,INT((C5-C4)/7)+1)) -> 3 | E6: 3. At the end of each week, copy Overall progress (Tracker J32) into the Weekly sheet, column D.
E7: Blue text on yellow = editable. Weeks and effort days are planning estimates; change them freely (columns D to F).
A8: ID | B8: Work stream | C8: Task | D8: Start wk | E8: End wk | F8: Effort (days) | G8: Start date | H8: End date | I8: Status | J8: Progress % | K8: Planned % (this week) | L8: Against plan (pts) | M8: Flag | N8: Notes
A9: T01 | B9: Foundation | C9: Project setup, architecture, UI/UX foundation | D9: 1 | E9: 1 | F9: 5 | G9: =$C$4+(D9-1)*7 -> 46280 | H9: =$C$4+E9*7-1 -> 46286 | I9: Done | J9: =IFERROR(VLOOKUP(I9,Lists!$A$5:$B$8,2,FALSE()),0) -> 1 | K9: =MAX(0,MIN(1,($C$6-D9+1)/(E9-D9+1))) -> 1 | L9: =(J9-K9)*100 -> 0 | M9: =IF(AND($C$6>0,J9<1,K9-J9>=0.25),"Behind plan","") | N9: Laravel 12 + Inertia/React + Fortify + Spatie. Ops layout (AppShell, sidebar, topbar) and shared UI kit are in place.
A10: T02 | B10: Foundation | C10: Database design and multi-tenant setup | D10: 1 | E10: 3 | F10: 8 | G10: =$C$4+(D10-1)*7 -> 46280 | H10: =$C$4+E10*7-1 -> 46300 | I10: In progress | J10: =IFERROR(VLOOKUP(I10,Lists!$A$5:$B$8,2,FALSE()),0) -> 0.5 | K10: =MAX(0,MIN(1,($C$6-D10+1)/(E10-D10+1))) -> 1 | L10: =(J10-K10)*100 -> -50 | M10: =IF(AND($C$6>0,J10<1,K10-J10>=0.25),"Behind plan","") -> Behind plan | N10: Migrations done: companies, branches, employees, activity_logs, users tenancy, permission tables, BelongsToCompany. Tables for attendance, leave, payroll, loans etc. not yet created.
A11: T03 | B11: Foundation | C11: Login, password reset, roles and permissions | D11: 1 | E11: 3 | F11: 8 | G11: =$C$4+(D11-1)*7 -> 46280 | H11: =$C$4+E11*7-1 -> 46300 | I11: In progress | J11: =IFERROR(VLOOKUP(I11,Lists!$A$5:$B$8,2,FALSE()),0) -> 0.5 | K11: =MAX(0,MIN(1,($C$6-D11+1)/(E11-D11+1))) -> 1 | L11: =(J11-K11)*100 -> -50 | M11: =IF(AND($C$6>0,J11<1,K11-J11>=0.25),"Behind plan","") -> Behind plan | N11: Backend live: Fortify login/forgot/reset, active-user middleware, 6 roles with Spatie permissions. Login/forgot/reset pages built. Role editing UI still on mock data.
A12: T04 | B12: Foundation | C12: User accounts, access and activity logs | D12: 2 | E12: 3 | F12: 5 | G12: =$C$4+(D12-1)*7 -> 46287 | H12: =$C$4+E12*7-1 -> 46300 | I12: In progress | J12: =IFERROR(VLOOKUP(I12,Lists!$A$5:$B$8,2,FALSE()),0) -> 0.5 | K12: =MAX(0,MIN(1,($C$6-D12+1)/(E12-D12+1))) -> 1 | L12: =(J12-K12)*100 -> -50 | M12: =IF(AND($C$6>0,J12<1,K12-J12>=0.25),"Behind plan","") -> Behind plan | N12: User Access page built (FE, mock). ActivityLogger + model exist for employee create/update only. No user CRUD backend yet.
A13: T05 | B13: Foundation | C13: Company information, payroll settings, holidays | D13: 2 | E13: 3 | F13: 6 | G13: =$C$4+(D13-1)*7 -> 46287 | H13: =$C$4+E13*7-1 -> 46300 | I13: In progress | J13: =IFERROR(VLOOKUP(I13,Lists!$A$5:$B$8,2,FALSE()),0) -> 0.5 | K13: =MAX(0,MIN(1,($C$6-D13+1)/(E13-D13+1))) -> 1 | L13: =(J13-K13)*100 -> -50 | M13: =IF(AND($C$6>0,J13<1,K13-J13>=0.25),"Behind plan","") -> Behind plan | N13: Company Settings page built (FE, mock/local stores). Backend controller and persistence pending.
A14: T06 | B14: Foundation | C14: Branches and onboarding | D14: 3 | E14: 3 | F14: 5 | G14: =$C$4+(D14-1)*7 -> 46294 | H14: =$C$4+E14*7-1 -> 46300 | I14: In progress | J14: =IFERROR(VLOOKUP(I14,Lists!$A$5:$B$8,2,FALSE()),0) -> 0.5 | K14: =MAX(0,MIN(1,($C$6-D14+1)/(E14-D14+1))) -> 1 | L14: =(J14-K14)*100 -> -50 | M14: =IF(AND($C$6>0,J14<1,K14-J14>=0.25),"Behind plan","") -> Behind plan | N14: Branches and Onboarding pages built (FE, mock). Branch model exists; no controller or API.
A15: T07 | B15: Workforce and time | C15: Employee management (list, profile, import) | D15: 2 | E15: 3 | F15: 10 | G15: =$C$4+(D15-1)*7 -> 46287 | H15: =$C$4+E15*7-1 -> 46300 | I15: In progress | J15: =IFERROR(VLOOKUP(I15,Lists!$A$5:$B$8,2,FALSE()),0) -> 0.5 | K15: =MAX(0,MIN(1,($C$6-D15+1)/(E15-D15+1))) -> 1 | L15: =(J15-K15)*100 -> -50 | M15: =IF(AND($C$6>0,J15<1,K15-J15>=0.25),"Behind plan","") -> Behind plan | N15: FE list + profile (incl. compensation, import) built. Backend: store/update endpoints + validation + activity log done. List/show still read mock data.
A16: T08 | B16: Workforce and time | C16: Attendance, adjustments and biometrics | D16: 3 | E16: 4 | F16: 12 | G16: =$C$4+(D16-1)*7 -> 46294 | H16: =$C$4+E16*7-1 -> 46307 | I16: In progress | J16: =IFERROR(VLOOKUP(I16,Lists!$A$5:$B$8,2,FALSE()),0) -> 0.5 | K16: =MAX(0,MIN(1,($C$6-D16+1)/(E16-D16+1))) -> 0.5 | L16: =(J16-K16)*100 -> 0 | M16: =IF(AND($C$6>0,J16<1,K16-J16>=0.25),"Behind plan","") | N16: Attendance page + biometrics import and schedule review utilities built (FE, mock). No attendance tables or API yet.
A17: T09 | B17: Workforce and time | C17: Schedules (roster, teams, shift templates) | D17: 3 | E17: 4 | F17: 8 | G17: =$C$4+(D17-1)*7 -> 46294 | H17: =$C$4+E17*7-1 -> 46307 | I17: In progress | J17: =IFERROR(VLOOKUP(I17,Lists!$A$5:$B$8,2,FALSE()),0) -> 0.5 | K17: =MAX(0,MIN(1,($C$6-D17+1)/(E17-D17+1))) -> 0.5 | L17: =(J17-K17)*100 -> 0 | M17: =IF(AND($C$6>0,J17<1,K17-J17>=0.25),"Behind plan","") | N17: Roster, Teams and supervisors, Shift templates tabs built (FE, mock). Backend pending.
A18: T10 | B18: Workforce and time | C18: Leave types, requests, approvals and balances | D18: 4 | E18: 5 | F18: 8 | G18: =$C$4+(D18-1)*7 -> 46301 | H18: =$C$4+E18*7-1 -> 46314 | I18: In progress | J18: =IFERROR(VLOOKUP(I18,Lists!$A$5:$B$8,2,FALSE()),0) -> 0.5 | K18: =MAX(0,MIN(1,($C$6-D18+1)/(E18-D18+1))) -> 0 | L18: =(J18-K18)*100 -> 50 | M18: =IF(AND($C$6>0,J18<1,K18-J18>=0.25),"Behind plan","") | N18: Leave page built (FE, mock). Backend pending.
A19: T11 | B19: Workforce and time | C19: Overtime and night differential | D19: 4 | E19: 5 | F19: 6 | G19: =$C$4+(D19-1)*7 -> 46301 | H19: =$C$4+E19*7-1 -> 46314 | I19: In progress | J19: =IFERROR(VLOOKUP(I19,Lists!$A$5:$B$8,2,FALSE()),0) -> 0.5 | K19: =MAX(0,MIN(1,($C$6-D19+1)/(E19-D19+1))) -> 0 | L19: =(J19-K19)*100 -> 50 | M19: =IF(AND($C$6>0,J19<1,K19-J19>=0.25),"Behind plan","") | N19: Overtime page + ESS OT application built (FE, mock). Backend pending.
A20: T12 | B20: Workforce and time | C20: Hourly and output compensation approvals | D20: 5 | E20: 6 | F20: 6 | G20: =$C$4+(D20-1)*7 -> 46308 | H20: =$C$4+E20*7-1 -> 46321 | I20: In progress | J20: =IFERROR(VLOOKUP(I20,Lists!$A$5:$B$8,2,FALSE()),0) -> 0.5 | K20: =MAX(0,MIN(1,($C$6-D20+1)/(E20-D20+1))) -> 0 | L20: =(J20-K20)*100 -> 50 | M20: =IF(AND($C$6>0,J20<1,K20-J20>=0.25),"Behind plan","") | N20: Approvals page built (FE, mock). Backend pending.
... A31: T23 | B31: Portals, platform and launch | C31: UAT, pilot and go-live | D31: 10 | E31: 11 | F31: 8 | G31: =$C$4+(D31-1)*7 -> 46343 | H31: =$C$4+E31*7-1 -> 46356 | I31: Not started | J31: =IFERROR(VLOOKUP(I31,Lists!$A$5:$B$8,2,FALSE()),0) -> 0 | K31: =MAX(0,MIN(1,($C$6-D31+1)/(E31-D31+1))) -> 0 | L31: =(J31-K31)*100 -> 0 | M31: =IF(AND($C$6>0,J31<1,K31-J31>=0.25),"Behind plan","") | N31: Not started.
A32: Total / overall | F32: =SUM(F9:F31) -> 191 | J32: =SUMPRODUCT(F9:F31,J9:J31)/F32 -> 0.45549738 | K32: =SUMPRODUCT(F9:F31,K9:K31)/F32 -> 0.29842932 | L32: =(J32-K32)*100 -> 15.706806
A34: Notes: Status drives Progress %; overall progress is weighted by effort days. 'Behind plan' = at least 25 points behind the planned % for the current week. Points = percentage points.

Sheet Schedule
A1: Schedule: weekly plan with progress (target finish Nov 30, 2026)
A2: ="Project Owner: "&Tracker!$C$3&" | Light teal = scheduled weeks, dark teal = share complete, amber = current week" -> Project Owner: Thea Consignado | Light teal = scheduled weeks, dark teal = share complete, amber = current week
C3: Month 1 | G3: Month 2 | K3: Month 3
A4: ID | B4: Task | C4: 1 | D4: 2 | E4: 3 | F4: 4 | G4: 5 | H4: 6 | I4: 7 | J4: 8 | K4: 9 | L4: 10 | M4: 11 | N4: 12 | O4: 13 | P4: Progress
B5: Week starts | C5: =Tracker!$C$4+(C$4-1)*7 -> 46280 | D5: =Tracker!$C$4+(D$4-1)*7 -> 46287 | E5: =Tracker!$C$4+(E$4-1)*7 -> 46294 | F5: =Tracker!$C$4+(F$4-1)*7 -> 46301 | G5: =Tracker!$C$4+(G$4-1)*7 -> 46308 | H5: =Tracker!$C$4+(H$4-1)*7 -> 46315 | I5: =Tracker!$C$4+(I$4-1)*7 -> 46322 | J5: =Tracker!$C$4+(J$4-1)*7 -> 46329 | ... O5: =Tracker!$C$4+(O$4-1)*7 -> 46364
A6: =Tracker!A9 -> T01 | B6: =Tracker!C9 -> Project setup, architecture, UI/UX foundation | C6: =IF(AND(C$4>=Tracker!$D9,C$4<=Tracker!$E9),IF((C$4-Tracker!$D9+1)/(Tracker!$E9-Tracker!$D9+1)<=Tracker!$J9+0.0001,2,1),0) -> 2 | D6: =IF(AND(D$4>=Tracker!$D9,D$4<=Tracker!$E9),IF((D$4-Tracker!$D9+1)/(Tracker!$E9-Tracker!$D9+1)<=Tracker!$J9+0.0001,2,1),0) -> 0 | E6: =IF(AND(E$4>=Tracker!$D9,E$4<=Tracker!$E9),IF((E$4-Tracker!$D9+1)/(Tracker!$E9-Tracker!$D9+1)<=Tracker!$J9+0.0001,2,1),0) -> 0 | F6: =IF(AND(F$4>=Tracker!$D9,F$4<=Tracker!$E9),IF((F$4-Tracker!$D9+1)/(Tracker!$E9-Tracker!$D9+1)<=Tracker!$J9+0.0001,2,1),0) -> 0 | G6: =IF(AND(G$4>=Tracker!$D9,G$4<=Tracker!$E9),IF((G$4-Tracker!$D9+1)/(Tracker!$E9-Tracker!$D9+1)<=Tracker!$J9+0.0001,2,1),0) -> 0 | H6: =IF(AND(H$4>=Tracker!$D9,H$4<=Tracker!$E9),IF((H$4-Tracker!$D9+1)/(Tracker!$E9-Tracker!$D9+1)<=Tracker!$J9+0.0001,2,1),0) -> 0 | I6: =IF(AND(I$4>=Tracker!$D9,I$4<=Tracker!$E9),IF((I$4-Tracker!$D9+1)/(Tracker!$E9-Tracker!$D9+1)<=Tracker!$J9+0.0001,2,1),0) -> 0 | J6: =IF(AND(J$4>=Tracker!$D9,J$4<=Tracker!$E9),IF((J$4-Tracker!$D9+1)/(Tracker!$E9-Tracker!$D9+1)<=Tracker!$J9+0.0001,2,1),0) -> 0 | ... O6: =IF(AND(O$4>=Tracker!$D9,O$4<=Tracker!$E9),IF((O$4-Tracker!$D9+1)/(Tracker!$E9-Tracker!$D9+1)<=Tracker!$J9+0.0001,2,1),0) -> 0 | P6: =Tracker!J9 -> 1
A7: =Tracker!A10 -> T02 | B7: =Tracker!C10 -> Database design and multi-tenant setup | C7: =IF(AND(C$4>=Tracker!$D10,C$4<=Tracker!$E10),IF((C$4-Tracker!$D10+1)/(Tracker!$E10-Tracker!$D10+1)<=Tracker!$J10+0.0001,2,1),0) -> 2 | D7: =IF(AND(D$4>=Tracker!$D10,D$4<=Tracker!$E10),IF((D$4-Tracker!$D10+1)/(Tracker!$E10-Tracker!$D10+1)<=Tracker!$J10+0.0001,2,1),0) -> 1 | E7: =IF(AND(E$4>=Tracker!$D10,E$4<=Tracker!$E10),IF((E$4-Tracker!$D10+1)/(Tracker!$E10-Tracker!$D10+1)<=Tracker!$J10+0.0001,2,1),0) -> 1 | F7: =IF(AND(F$4>=Tracker!$D10,F$4<=Tracker!$E10),IF((F$4-Tracker!$D10+1)/(Tracker!$E10-Tracker!$D10+1)<=Tracker!$J10+0.0001,2,1),0) -> 0 | G7: =IF(AND(G$4>=Tracker!$D10,G$4<=Tracker!$E10),IF((G$4-Tracker!$D10+1)/(Tracker!$E10-Tracker!$D10+1)<=Tracker!$J10+0.0001,2,1),0) -> 0 | H7: =IF(AND(H$4>=Tracker!$D10,H$4<=Tracker!$E10),IF((H$4-Tracker!$D10+1)/(Tracker!$E10-Tracker!$D10+1)<=Tracker!$J10+0.0001,2,1),0) -> 0 | I7: =IF(AND(I$4>=Tracker!$D10,I$4<=Tracker!$E10),IF((I$4-Tracker!$D10+1)/(Tracker!$E10-Tracker!$D10+1)<=Tracker!$J10+0.0001,2,1),0) -> 0 | J7: =IF(AND(J$4>=Tracker!$D10,J$4<=Tracker!$E10),IF((J$4-Tracker!$D10+1)/(Tracker!$E10-Tracker!$D10+1)<=Tracker!$J10+0.0001,2,1),0) -> 0 | ... O7: =IF(AND(O$4>=Tracker!$D10,O$4<=Tracker!$E10),IF((O$4-Tracker!$D10+1)/(Tracker!$E10-Tracker!$D10+1)<=Tracker!$J10+0.0001,2,1),0) -> 0 | P7: =Tracker!J10 -> 0.5
A8: =Tracker!A11 -> T03 | B8: =Tracker!C11 -> Login, password reset, roles and permissions | C8: =IF(AND(C$4>=Tracker!$D11,C$4<=Tracker!$E11),IF((C$4-Tracker!$D11+1)/(Tracker!$E11-Tracker!$D11+1)<=Tracker!$J11+0.0001,2,1),0) -> 2 | D8: =IF(AND(D$4>=Tracker!$D11,D$4<=Tracker!$E11),IF((D$4-Tracker!$D11+1)/(Tracker!$E11-Tracker!$D11+1)<=Tracker!$J11+0.0001,2,1),0) -> 1 | E8: =IF(AND(E$4>=Tracker!$D11,E$4<=Tracker!$E11),IF((E$4-Tracker!$D11+1)/(Tracker!$E11-Tracker!$D11+1)<=Tracker!$J11+0.0001,2,1),0) -> 1 | F8: =IF(AND(F$4>=Tracker!$D11,F$4<=Tracker!$E11),IF((F$4-Tracker!$D11+1)/(Tracker!$E11-Tracker!$D11+1)<=Tracker!$J11+0.0001,2,1),0) -> 0 | G8: =IF(AND(G$4>=Tracker!$D11,G$4<=Tracker!$E11),IF((G$4-Tracker!$D11+1)/(Tracker!$E11-Tracker!$D11+1)<=Tracker!$J11+0.0001,2,1),0) -> 0 | H8: =IF(AND(H$4>=Tracker!$D11,H$4<=Tracker!$E11),IF((H$4-Tracker!$D11+1)/(Tracker!$E11-Tracker!$D11+1)<=Tracker!$J11+0.0001,2,1),0) -> 0 | I8: =IF(AND(I$4>=Tracker!$D11,I$4<=Tracker!$E11),IF((I$4-Tracker!$D11+1)/(Tracker!$E11-Tracker!$D11+1)<=Tracker!$J11+0.0001,2,1),0) -> 0 | J8: =IF(AND(J$4>=Tracker!$D11,J$4<=Tracker!$E11),IF((J$4-Tracker!$D11+1)/(Tracker!$E11-Tracker!$D11+1)<=Tracker!$J11+0.0001,2,1),0) -> 0 | ... O8: =IF(AND(O$4>=Tracker!$D11,O$4<=Tracker!$E11),IF((O$4-Tracker!$D11+1)/(Tracker!$E11-Tracker!$D11+1)<=Tracker!$J11+0.0001,2,1),0) -> 0 | P8: =Tracker!J11 -> 0.5
A9: =Tracker!A12 -> T04 | B9: =Tracker!C12 -> User accounts, access and activity logs | C9: =IF(AND(C$4>=Tracker!$D12,C$4<=Tracker!$E12),IF((C$4-Tracker!$D12+1)/(Tracker!$E12-Tracker!$D12+1)<=Tracker!$J12+0.0001,2,1),0) -> 0 | D9: =IF(AND(D$4>=Tracker!$D12,D$4<=Tracker!$E12),IF((D$4-Tracker!$D12+1)/(Tracker!$E12-Tracker!$D12+1)<=Tracker!$J12+0.0001,2,1),0) -> 2 | E9: =IF(AND(E$4>=Tracker!$D12,E$4<=Tracker!$E12),IF((E$4-Tracker!$D12+1)/(Tracker!$E12-Tracker!$D12+1)<=Tracker!$J12+0.0001,2,1),0) -> 1 | F9: =IF(AND(F$4>=Tracker!$D12,F$4<=Tracker!$E12),IF((F$4-Tracker!$D12+1)/(Tracker!$E12-Tracker!$D12+1)<=Tracker!$J12+0.0001,2,1),0) -> 0 | G9: =IF(AND(G$4>=Tracker!$D12,G$4<=Tracker!$E12),IF((G$4-Tracker!$D12+1)/(Tracker!$E12-Tracker!$D12+1)<=Tracker!$J12+0.0001,2,1),0) -> 0 | H9: =IF(AND(H$4>=Tracker!$D12,H$4<=Tracker!$E12),IF((H$4-Tracker!$D12+1)/(Tracker!$E12-Tracker!$D12+1)<=Tracker!$J12+0.0001,2,1),0) -> 0 | I9: =IF(AND(I$4>=Tracker!$D12,I$4<=Tracker!$E12),IF((I$4-Tracker!$D12+1)/(Tracker!$E12-Tracker!$D12+1)<=Tracker!$J12+0.0001,2,1),0) -> 0 | J9: =IF(AND(J$4>=Tracker!$D12,J$4<=Tracker!$E12),IF((J$4-Tracker!$D12+1)/(Tracker!$E12-Tracker!$D12+1)<=Tracker!$J12+0.0001,2,1),0) -> 0 | ... O9: =IF(AND(O$4>=Tracker!$D12,O$4<=Tracker!$E12),IF((O$4-Tracker!$D12+1)/(Tracker!$E12-Tracker!$D12+1)<=Tracker!$J12+0.0001,2,1),0) -> 0 | P9: =Tracker!J12 -> 0.5
A10: =Tracker!A13 -> T05 | B10: =Tracker!C13 -> Company information, payroll settings, holidays | C10: =IF(AND(C$4>=Tracker!$D13,C$4<=Tracker!$E13),IF((C$4-Tracker!$D13+1)/(Tracker!$E13-Tracker!$D13+1)<=Tracker!$J13+0.0001,2,1),0) -> 0 | D10: =IF(AND(D$4>=Tracker!$D13,D$4<=Tracker!$E13),IF((D$4-Tracker!$D13+1)/(Tracker!$E13-Tracker!$D13+1)<=Tracker!$J13+0.0001,2,1),0) -> 2 | E10: =IF(AND(E$4>=Tracker!$D13,E$4<=Tracker!$E13),IF((E$4-Tracker!$D13+1)/(Tracker!$E13-Tracker!$D13+1)<=Tracker!$J13+0.0001,2,1),0) -> 1 | F10: =IF(AND(F$4>=Tracker!$D13,F$4<=Tracker!$E13),IF((F$4-Tracker!$D13+1)/(Tracker!$E13-Tracker!$D13+1)<=Tracker!$J13+0.0001,2,1),0) -> 0 | G10: =IF(AND(G$4>=Tracker!$D13,G$4<=Tracker!$E13),IF((G$4-Tracker!$D13+1)/(Tracker!$E13-Tracker!$D13+1)<=Tracker!$J13+0.0001,2,1),0) -> 0 | H10: =IF(AND(H$4>=Tracker!$D13,H$4<=Tracker!$E13),IF((H$4-Tracker!$D13+1)/(Tracker!$E13-Tracker!$D13+1)<=Tracker!$J13+0.0001,2,1),0) -> 0 | I10: =IF(AND(I$4>=Tracker!$D13,I$4<=Tracker!$E13),IF((I$4-Tracker!$D13+1)/(Tracker!$E13-Tracker!$D13+1)<=Tracker!$J13+0.0001,2,1),0) -> 0 | J10: =IF(AND(J$4>=Tracker!$D13,J$4<=Tracker!$E13),IF((J$4-Tracker!$D13+1)/(Tracker!$E13-Tracker!$D13+1)<=Tracker!$J13+0.0001,2,1),0) -> 0 | ... O10: =IF(AND(O$4>=Tracker!$D13,O$4<=Tracker!$E13),IF((O$4-Tracker!$D13+1)/(Tracker!$E13-Tracker!$D13+1)<=Tracker!$J13+0.0001,2,1),0) -> 0 | P10: =Tracker!J13 -> 0.5
A11: =Tracker!A14 -> T06 | B11: =Tracker!C14 -> Branches and onboarding | C11: =IF(AND(C$4>=Tracker!$D14,C$4<=Tracker!$E14),IF((C$4-Tracker!$D14+1)/(Tracker!$E14-Tracker!$D14+1)<=Tracker!$J14+0.0001,2,1),0) -> 0 | D11: =IF(AND(D$4>=Tracker!$D14,D$4<=Tracker!$E14),IF((D$4-Tracker!$D14+1)/(Tracker!$E14-Tracker!$D14+1)<=Tracker!$J14+0.0001,2,1),0) -> 0 | E11: =IF(AND(E$4>=Tracker!$D14,E$4<=Tracker!$E14),IF((E$4-Tracker!$D14+1)/(Tracker!$E14-Tracker!$D14+1)<=Tracker!$J14+0.0001,2,1),0) -> 1 | F11: =IF(AND(F$4>=Tracker!$D14,F$4<=Tracker!$E14),IF((F$4-Tracker!$D14+1)/(Tracker!$E14-Tracker!$D14+1)<=Tracker!$J14+0.0001,2,1),0) -> 0 | G11: =IF(AND(G$4>=Tracker!$D14,G$4<=Tracker!$E14),IF((G$4-Tracker!$D14+1)/(Tracker!$E14-Tracker!$D14+1)<=Tracker!$J14+0.0001,2,1),0) -> 0 | H11: =IF(AND(H$4>=Tracker!$D14,H$4<=Tracker!$E14),IF((H$4-Tracker!$D14+1)/(Tracker!$E14-Tracker!$D14+1)<=Tracker!$J14+0.0001,2,1),0) -> 0 | I11: =IF(AND(I$4>=Tracker!$D14,I$4<=Tracker!$E14),IF((I$4-Tracker!$D14+1)/(Tracker!$E14-Tracker!$D14+1)<=Tracker!$J14+0.0001,2,1),0) -> 0 | J11: =IF(AND(J$4>=Tracker!$D14,J$4<=Tracker!$E14),IF((J$4-Tracker!$D14+1)/(Tracker!$E14-Tracker!$D14+1)<=Tracker!$J14+0.0001,2,1),0) -> 0 | ... O11: =IF(AND(O$4>=Tracker!$D14,O$4<=Tracker!$E14),IF((O$4-Tracker!$D14+1)/(Tracker!$E14-Tracker!$D14+1)<=Tracker!$J14+0.0001,2,1),0) -> 0 | P11: =Tracker!J14 -> 0.5
A12: =Tracker!A15 -> T07 | B12: =Tracker!C15 -> Employee management (list, profile, import) | C12: =IF(AND(C$4>=Tracker!$D15,C$4<=Tracker!$E15),IF((C$4-Tracker!$D15+1)/(Tracker!$E15-Tracker!$D15+1)<=Tracker!$J15+0.0001,2,1),0) -> 0 | D12: =IF(AND(D$4>=Tracker!$D15,D$4<=Tracker!$E15),IF((D$4-Tracker!$D15+1)/(Tracker!$E15-Tracker!$D15+1)<=Tracker!$J15+0.0001,2,1),0) -> 2 | E12: =IF(AND(E$4>=Tracker!$D15,E$4<=Tracker!$E15),IF((E$4-Tracker!$D15+1)/(Tracker!$E15-Tracker!$D15+1)<=Tracker!$J15+0.0001,2,1),0) -> 1 | F12: =IF(AND(F$4>=Tracker!$D15,F$4<=Tracker!$E15),IF((F$4-Tracker!$D15+1)/(Tracker!$E15-Tracker!$D15+1)<=Tracker!$J15+0.0001,2,1),0) -> 0 | G12: =IF(AND(G$4>=Tracker!$D15,G$4<=Tracker!$E15),IF((G$4-Tracker!$D15+1)/(Tracker!$E15-Tracker!$D15+1)<=Tracker!$J15+0.0001,2,1),0) -> 0 | H12: =IF(AND(H$4>=Tracker!$D15,H$4<=Tracker!$E15),IF((H$4-Tracker!$D15+1)/(Tracker!$E15-Tracker!$D15+1)<=Tracker!$J15+0.0001,2,1),0) -> 0 | I12: =IF(AND(I$4>=Tracker!$D15,I$4<=Tracker!$E15),IF((I$4-Tracker!$D15+1)/(Tracker!$E15-Tracker!$D15+1)<=Tracker!$J15+0.0001,2,1),0) -> 0 | J12: =IF(AND(J$4>=Tracker!$D15,J$4<=Tracker!$E15),IF((J$4-Tracker!$D15+1)/(Tracker!$E15-Tracker!$D15+1)<=Tracker!$J15+0.0001,2,1),0) -> 0 | ... O12: =IF(AND(O$4>=Tracker!$D15,O$4<=Tracker!$E15),IF((O$4-Tracker!$D15+1)/(Tracker!$E15-Tracker!$D15+1)<=Tracker!$J15+0.0001,2,1),0) -> 0 | P12: =Tracker!J15 -> 0.5
A13: =Tracker!A16 -> T08 | B13: =Tracker!C16 -> Attendance, adjustments and biometrics | C13: =IF(AND(C$4>=Tracker!$D16,C$4<=Tracker!$E16),IF((C$4-Tracker!$D16+1)/(Tracker!$E16-Tracker!$D16+1)<=Tracker!$J16+0.0001,2,1),0) -> 0 | D13: =IF(AND(D$4>=Tracker!$D16,D$4<=Tracker!$E16),IF((D$4-Tracker!$D16+1)/(Tracker!$E16-Tracker!$D16+1)<=Tracker!$J16+0.0001,2,1),0) -> 0 | E13: =IF(AND(E$4>=Tracker!$D16,E$4<=Tracker!$E16),IF((E$4-Tracker!$D16+1)/(Tracker!$E16-Tracker!$D16+1)<=Tracker!$J16+0.0001,2,1),0) -> 2 | F13: =IF(AND(F$4>=Tracker!$D16,F$4<=Tracker!$E16),IF((F$4-Tracker!$D16+1)/(Tracker!$E16-Tracker!$D16+1)<=Tracker!$J16+0.0001,2,1),0) -> 1 | G13: =IF(AND(G$4>=Tracker!$D16,G$4<=Tracker!$E16),IF((G$4-Tracker!$D16+1)/(Tracker!$E16-Tracker!$D16+1)<=Tracker!$J16+0.0001,2,1),0) -> 0 | H13: =IF(AND(H$4>=Tracker!$D16,H$4<=Tracker!$E16),IF((H$4-Tracker!$D16+1)/(Tracker!$E16-Tracker!$D16+1)<=Tracker!$J16+0.0001,2,1),0) -> 0 | I13: =IF(AND(I$4>=Tracker!$D16,I$4<=Tracker!$E16),IF((I$4-Tracker!$D16+1)/(Tracker!$E16-Tracker!$D16+1)<=Tracker!$J16+0.0001,2,1),0) -> 0 | J13: =IF(AND(J$4>=Tracker!$D16,J$4<=Tracker!$E16),IF((J$4-Tracker!$D16+1)/(Tracker!$E16-Tracker!$D16+1)<=Tracker!$J16+0.0001,2,1),0) -> 0 | ... O13: =IF(AND(O$4>=Tracker!$D16,O$4<=Tracker!$E16),IF((O$4-Tracker!$D16+1)/(Tracker!$E16-Tracker!$D16+1)<=Tracker!$J16+0.0001,2,1),0) -> 0 | P13: =Tracker!J16 -> 0.5
A14: =Tracker!A17 -> T09 | B14: =Tracker!C17 -> Schedules (roster, teams, shift templates) | C14: =IF(AND(C$4>=Tracker!$D17,C$4<=Tracker!$E17),IF((C$4-Tracker!$D17+1)/(Tracker!$E17-Tracker!$D17+1)<=Tracker!$J17+0.0001,2,1),0) -> 0 | D14: =IF(AND(D$4>=Tracker!$D17,D$4<=Tracker!$E17),IF((D$4-Tracker!$D17+1)/(Tracker!$E17-Tracker!$D17+1)<=Tracker!$J17+0.0001,2,1),0) -> 0 | E14: =IF(AND(E$4>=Tracker!$D17,E$4<=Tracker!$E17),IF((E$4-Tracker!$D17+1)/(Tracker!$E17-Tracker!$D17+1)<=Tracker!$J17+0.0001,2,1),0) -> 2 | F14: =IF(AND(F$4>=Tracker!$D17,F$4<=Tracker!$E17),IF((F$4-Tracker!$D17+1)/(Tracker!$E17-Tracker!$D17+1)<=Tracker!$J17+0.0001,2,1),0) -> 1 | G14: =IF(AND(G$4>=Tracker!$D17,G$4<=Tracker!$E17),IF((G$4-Tracker!$D17+1)/(Tracker!$E17-Tracker!$D17+1)<=Tracker!$J17+0.0001,2,1),0) -> 0 | H14: =IF(AND(H$4>=Tracker!$D17,H$4<=Tracker!$E17),IF((H$4-Tracker!$D17+1)/(Tracker!$E17-Tracker!$D17+1)<=Tracker!$J17+0.0001,2,1),0) -> 0 | I14: =IF(AND(I$4>=Tracker!$D17,I$4<=Tracker!$E17),IF((I$4-Tracker!$D17+1)/(Tracker!$E17-Tracker!$D17+1)<=Tracker!$J17+0.0001,2,1),0) -> 0 | J14: =IF(AND(J$4>=Tracker!$D17,J$4<=Tracker!$E17),IF((J$4-Tracker!$D17+1)/(Tracker!$E17-Tracker!$D17+1)<=Tracker!$J17+0.0001,2,1),0) -> 0 | ... O14: =IF(AND(O$4>=Tracker!$D17,O$4<=Tracker!$E17),IF((O$4-Tracker!$D17+1)/(Tracker!$E17-Tracker!$D17+1)<=Tracker!$J17+0.0001,2,1),0) -> 0 | P14: =Tracker!J17 -> 0.5
A15: =Tracker!A18 -> T10 | B15: =Tracker!C18 -> Leave types, requests, approvals and balances | C15: =IF(AND(C$4>=Tracker!$D18,C$4<=Tracker!$E18),IF((C$4-Tracker!$D18+1)/(Tracker!$E18-Tracker!$D18+1)<=Tracker!$J18+0.0001,2,1),0) -> 0 | D15: =IF(AND(D$4>=Tracker!$D18,D$4<=Tracker!$E18),IF((D$4-Tracker!$D18+1)/(Tracker!$E18-Tracker!$D18+1)<=Tracker!$J18+0.0001,2,1),0) -> 0 | E15: =IF(AND(E$4>=Tracker!$D18,E$4<=Tracker!$E18),IF((E$4-Tracker!$D18+1)/(Tracker!$E18-Tracker!$D18+1)<=Tracker!$J18+0.0001,2,1),0) -> 0 | F15: =IF(AND(F$4>=Tracker!$D18,F$4<=Tracker!$E18),IF((F$4-Tracker!$D18+1)/(Tracker!$E18-Tracker!$D18+1)<=Tracker!$J18+0.0001,2,1),0) -> 2 | G15: =IF(AND(G$4>=Tracker!$D18,G$4<=Tracker!$E18),IF((G$4-Tracker!$D18+1)/(Tracker!$E18-Tracker!$D18+1)<=Tracker!$J18+0.0001,2,1),0) -> 1 | H15: =IF(AND(H$4>=Tracker!$D18,H$4<=Tracker!$E18),IF((H$4-Tracker!$D18+1)/(Tracker!$E18-Tracker!$D18+1)<=Tracker!$J18+0.0001,2,1),0) -> 0 | I15: =IF(AND(I$4>=Tracker!$D18,I$4<=Tracker!$E18),IF((I$4-Tracker!$D18+1)/(Tracker!$E18-Tracker!$D18+1)<=Tracker!$J18+0.0001,2,1),0) -> 0 | J15: =IF(AND(J$4>=Tracker!$D18,J$4<=Tracker!$E18),IF((J$4-Tracker!$D18+1)/(Tracker!$E18-Tracker!$D18+1)<=Tracker!$J18+0.0001,2,1),0) -> 0 | ... O15: =IF(AND(O$4>=Tracker!$D18,O$4<=Tracker!$E18),IF((O$4-Tracker!$D18+1)/(Tracker!$E18-Tracker!$D18+1)<=Tracker!$J18+0.0001,2,1),0) -> 0 | P15: =Tracker!J18 -> 0.5
A16: =Tracker!A19 -> T11 | B16: =Tracker!C19 -> Overtime and night differential | C16: =IF(AND(C$4>=Tracker!$D19,C$4<=Tracker!$E19),IF((C$4-Tracker!$D19+1)/(Tracker!$E19-Tracker!$D19+1)<=Tracker!$J19+0.0001,2,1),0) -> 0 | D16: =IF(AND(D$4>=Tracker!$D19,D$4<=Tracker!$E19),IF((D$4-Tracker!$D19+1)/(Tracker!$E19-Tracker!$D19+1)<=Tracker!$J19+0.0001,2,1),0) -> 0 | E16: =IF(AND(E$4>=Tracker!$D19,E$4<=Tracker!$E19),IF((E$4-Tracker!$D19+1)/(Tracker!$E19-Tracker!$D19+1)<=Tracker!$J19+0.0001,2,1),0) -> 0 | F16: =IF(AND(F$4>=Tracker!$D19,F$4<=Tracker!$E19),IF((F$4-Tracker!$D19+1)/(Tracker!$E19-Tracker!$D19+1)<=Tracker!$J19+0.0001,2,1),0) -> 2 | G16: =IF(AND(G$4>=Tracker!$D19,G$4<=Tracker!$E19),IF((G$4-Tracker!$D19+1)/(Tracker!$E19-Tracker!$D19+1)<=Tracker!$J19+0.0001,2,1),0) -> 1 | H16: =IF(AND(H$4>=Tracker!$D19,H$4<=Tracker!$E19),IF((H$4-Tracker!$D19+1)/(Tracker!$E19-Tracker!$D19+1)<=Tracker!$J19+0.0001,2,1),0) -> 0 | I16: =IF(AND(I$4>=Tracker!$D19,I$4<=Tracker!$E19),IF((I$4-Tracker!$D19+1)/(Tracker!$E19-Tracker!$D19+1)<=Tracker!$J19+0.0001,2,1),0) -> 0 | J16: =IF(AND(J$4>=Tracker!$D19,J$4<=Tracker!$E19),IF((J$4-Tracker!$D19+1)/(Tracker!$E19-Tracker!$D19+1)<=Tracker!$J19+0.0001,2,1),0) -> 0 | ... O16: =IF(AND(O$4>=Tracker!$D19,O$4<=Tracker!$E19),IF((O$4-Tracker!$D19+1)/(Tracker!$E19-Tracker!$D19+1)<=Tracker!$J19+0.0001,2,1),0) -> 0 | P16: =Tracker!J19 -> 0.5
A17: =Tracker!A20 -> T12 | B17: =Tracker!C20 -> Hourly and output compensation approvals | C17: =IF(AND(C$4>=Tracker!$D20,C$4<=Tracker!$E20),IF((C$4-Tracker!$D20+1)/(Tracker!$E20-Tracker!$D20+1)<=Tracker!$J20+0.0001,2,1),0) -> 0 | D17: =IF(AND(D$4>=Tracker!$D20,D$4<=Tracker!$E20),IF((D$4-Tracker!$D20+1)/(Tracker!$E20-Tracker!$D20+1)<=Tracker!$J20+0.0001,2,1),0) -> 0 | E17: =IF(AND(E$4>=Tracker!$D20,E$4<=Tracker!$E20),IF((E$4-Tracker!$D20+1)/(Tracker!$E20-Tracker!$D20+1)<=Tracker!$J20+0.0001,2,1),0) -> 0 | F17: =IF(AND(F$4>=Tracker!$D20,F$4<=Tracker!$E20),IF((F$4-Tracker!$D20+1)/(Tracker!$E20-Tracker!$D20+1)<=Tracker!$J20+0.0001,2,1),0) -> 0 | G17: =IF(AND(G$4>=Tracker!$D20,G$4<=Tracker!$E20),IF((G$4-Tracker!$D20+1)/(Tracker!$E20-Tracker!$D20+1)<=Tracker!$J20+0.0001,2,1),0) -> 2 | H17: =IF(AND(H$4>=Tracker!$D20,H$4<=Tracker!$E20),IF((H$4-Tracker!$D20+1)/(Tracker!$E20-Tracker!$D20+1)<=Tracker!$J20+0.0001,2,1),0) -> 1 | I17: =IF(AND(I$4>=Tracker!$D20,I$4<=Tracker!$E20),IF((I$4-Tracker!$D20+1)/(Tracker!$E20-Tracker!$D20+1)<=Tracker!$J20+0.0001,2,1),0) -> 0 | J17: =IF(AND(J$4>=Tracker!$D20,J$4<=Tracker!$E20),IF((J$4-Tracker!$D20+1)/(Tracker!$E20-Tracker!$D20+1)<=Tracker!$J20+0.0001,2,1),0) -> 0 | ... O17: =IF(AND(O$4>=Tracker!$D20,O$4<=Tracker!$E20),IF((O$4-Tracker!$D20+1)/(Tracker!$E20-Tracker!$D20+1)<=Tracker!$J20+0.0001,2,1),0) -> 0 | P17: =Tracker!J20 -> 0.5
... A28: =Tracker!A31 -> T23 | B28: =Tracker!C31 -> UAT, pilot and go-live | C28: =IF(AND(C$4>=Tracker!$D31,C$4<=Tracker!$E31),IF((C$4-Tracker!$D31+1)/(Tracker!$E31-Tracker!$D31+1)<=Tracker!$J31+0.0001,2,1),0) -> 0 | D28: =IF(AND(D$4>=Tracker!$D31,D$4<=Tracker!$E31),IF((D$4-Tracker!$D31+1)/(Tracker!$E31-Tracker!$D31+1)<=Tracker!$J31+0.0001,2,1),0) -> 0 | E28: =IF(AND(E$4>=Tracker!$D31,E$4<=Tracker!$E31),IF((E$4-Tracker!$D31+1)/(Tracker!$E31-Tracker!$D31+1)<=Tracker!$J31+0.0001,2,1),0) -> 0 | F28: =IF(AND(F$4>=Tracker!$D31,F$4<=Tracker!$E31),IF((F$4-Tracker!$D31+1)/(Tracker!$E31-Tracker!$D31+1)<=Tracker!$J31+0.0001,2,1),0) -> 0 | G28: =IF(AND(G$4>=Tracker!$D31,G$4<=Tracker!$E31),IF((G$4-Tracker!$D31+1)/(Tracker!$E31-Tracker!$D31+1)<=Tracker!$J31+0.0001,2,1),0) -> 0 | H28: =IF(AND(H$4>=Tracker!$D31,H$4<=Tracker!$E31),IF((H$4-Tracker!$D31+1)/(Tracker!$E31-Tracker!$D31+1)<=Tracker!$J31+0.0001,2,1),0) -> 0 | I28: =IF(AND(I$4>=Tracker!$D31,I$4<=Tracker!$E31),IF((I$4-Tracker!$D31+1)/(Tracker!$E31-Tracker!$D31+1)<=Tracker!$J31+0.0001,2,1),0) -> 0 | J28: =IF(AND(J$4>=Tracker!$D31,J$4<=Tracker!$E31),IF((J$4-Tracker!$D31+1)/(Tracker!$E31-Tracker!$D31+1)<=Tracker!$J31+0.0001,2,1),0) -> 0 | ... O28: =IF(AND(O$4>=Tracker!$D31,O$4<=Tracker!$E31),IF((O$4-Tracker!$D31+1)/(Tracker!$E31-Tracker!$D31+1)<=Tracker!$J31+0.0001,2,1),0) -> 0 | P28: =Tracker!J31 -> 0

Sheet Weekly
A1: Weekly progress: planned vs actual
A2: ="Project Owner: "&Tracker!$C$3&" | Enter Actual % at the end of each week (copy Tracker J32). Leave future weeks blank." -> Project Owner: Thea Consignado | Enter Actual % at the end of each week (copy Tracker J32). Leave future weeks blank.
A4: Week | B4: Week starts | C4: Planned % | D4: Actual % (enter) | E4: Against plan (pts) | F4: Note
A5: 0 | B5: Start | C5: =SUMPRODUCT(Tracker!$F$9:$F$31,'Plan calc'!C$4:C$26)/Tracker!$F$32 -> 0 | D5: 0 | E5: =IF(D5="","",(D5-C5)*100) -> 0
A6: 1 | B6: =Tracker!$C$4+(1-1)*7 -> 46280 | C6: =SUMPRODUCT(Tracker!$F$9:$F$31,'Plan calc'!D$4:D$26)/Tracker!$F$32 -> 0.054101222 | E6: =IF(D6="","",(D6-C6)*100)
A7: 2 | B7: =Tracker!$C$4+(2-1)*7 -> 46287 | C7: =SUMPRODUCT(Tracker!$F$9:$F$31,'Plan calc'!E$4:E$26)/Tracker!$F$32 -> 0.13699825 | E7: =IF(D7="","",(D7-C7)*100)
A8: 3 | B8: =Tracker!$C$4+(3-1)*7 -> 46294 | C8: =SUMPRODUCT(Tracker!$F$9:$F$31,'Plan calc'!F$4:F$26)/Tracker!$F$32 -> 0.29842932 | E8: =IF(D8="","",(D8-C8)*100)
A9: 4 | B9: =Tracker!$C$4+(4-1)*7 -> 46301 | C9: =SUMPRODUCT(Tracker!$F$9:$F$31,'Plan calc'!G$4:G$26)/Tracker!$F$32 -> 0.38743455 | E9: =IF(D9="","",(D9-C9)*100)
A10: 5 | B10: =Tracker!$C$4+(5-1)*7 -> 46308 | C10: =SUMPRODUCT(Tracker!$F$9:$F$31,'Plan calc'!H$4:H$26)/Tracker!$F$32 -> 0.47905759 | E10: =IF(D10="","",(D10-C10)*100)
A11: 6 | B11: =Tracker!$C$4+(6-1)*7 -> 46315 | C11: =SUMPRODUCT(Tracker!$F$9:$F$31,'Plan calc'!I$4:I$26)/Tracker!$F$32 -> 0.56893543 | E11: =IF(D11="","",(D11-C11)*100)
A12: 7 | B12: =Tracker!$C$4+(7-1)*7 -> 46322 | C12: =SUMPRODUCT(Tracker!$F$9:$F$31,'Plan calc'!J$4:J$26)/Tracker!$F$32 -> 0.65881326 | E12: =IF(D12="","",(D12-C12)*100)
A13: 8 | B13: =Tracker!$C$4+(8-1)*7 -> 46329 | C13: =SUMPRODUCT(Tracker!$F$9:$F$31,'Plan calc'!K$4:K$26)/Tracker!$F$32 -> 0.77486911 | E13: =IF(D13="","",(D13-C13)*100)
A14: 9 | B14: =Tracker!$C$4+(9-1)*7 -> 46336 | C14: =SUMPRODUCT(Tracker!$F$9:$F$31,'Plan calc'!L$4:L$26)/Tracker!$F$32 -> 0.89354276 | E14: =IF(D14="","",(D14-C14)*100)
A15: 10 | B15: =Tracker!$C$4+(10-1)*7 -> 46343 | C15: =SUMPRODUCT(Tracker!$F$9:$F$31,'Plan calc'!M$4:M$26)/Tracker!$F$32 -> 0.95462478 | E15: =IF(D15="","",(D15-C15)*100)
A16: 11 | B16: =Tracker!$C$4+(11-1)*7 -> 46350 | C16: =SUMPRODUCT(Tracker!$F$9:$F$31,'Plan calc'!N$4:N$26)/Tracker!$F$32 -> 1 | E16: =IF(D16="","",(D16-C16)*100)
A17: 12 | B17: =Tracker!$C$4+(12-1)*7 -> 46357 | C17: =SUMPRODUCT(Tracker!$F$9:$F$31,'Plan calc'!O$4:O$26)/Tracker!$F$32 -> 1 | E17: =IF(D17="","",(D17-C17)*100)
A18: 13 | B18: =Tracker!$C$4+(13-1)*7 -> 46364 | C18: =SUMPRODUCT(Tracker!$F$9:$F$31,'Plan calc'!P$4:P$26)/Tracker!$F$32 -> 1 | E18: =IF(D18="","",(D18-C18)*100)

Sheet User Stories
A1: User Stories: Online Payroll System (OPS)
A2: ="Project Owner: "&Tracker!$C$3&" | Pick a Story status from the dropdown; Progress % is calculated from it" -> Project Owner: Thea Consignado | Pick a Story status from the dropdown; Progress % is calculated from it
A4: ID | B4: Module | C4: Role | D4: User story | E4: Acceptance criteria | F4: Priority | G4: Task | H4: Task status (from Tracker) | I4: Story status | J4: Progress %
A5: US01 | B5: Accounts and access | C5: Company Admin | D5: As a Company Admin, I want to log in securely and log out, so that only authorized staff can open payroll data. | E5: Login with email and password; inactive users are blocked; session ends on logout. | F5: Must | G5: T03 | H5: {=IFERROR(INDEX(Tracker!$I$9:$I$31,MATCH(G5,Tracker!$A$9:$A$31,0)),"")} -> In progress | I5: In progress | J5: =IFERROR(VLOOKUP(I5,Lists!$A$5:$B$8,2,FALSE()),0) -> 0.5
A6: US02 | B6: Accounts and access | C6: Any user | D6: As a user, I want to reset a forgotten password by email, so that I can regain access without calling support. | E6: Forgot password sends a reset link; reset page validates the token and password rules. | F6: Must | G6: T03 | H6: {=IFERROR(INDEX(Tracker!$I$9:$I$31,MATCH(G6,Tracker!$A$9:$A$31,0)),"")} -> In progress | I6: In progress | J6: =IFERROR(VLOOKUP(I6,Lists!$A$5:$B$8,2,FALSE()),0) -> 0.5
A7: US03 | B7: Accounts and access | C7: Company Admin | D7: As a Company Admin, I want to assign a role to each user (HR, Payroll, Manager, Employee), so that people only see what they need. | E7: Each role has a fixed permission list; unauthorized pages show a Forbidden page. | F7: Must | G7: T03 | H7: {=IFERROR(INDEX(Tracker!$I$9:$I$31,MATCH(G7,Tracker!$A$9:$A$31,0)),"")} -> In progress | I7: In progress | J7: =IFERROR(VLOOKUP(I7,Lists!$A$5:$B$8,2,FALSE()),0) -> 0.5
A8: US04 | B8: Accounts and access | C8: Company Admin | D8: As a Company Admin, I want to create users and edit their roles and permissions, so that access follows our org changes. | E8: Add, deactivate and edit users; permission changes apply on next request. | F8: Must | G8: T04 | H8: {=IFERROR(INDEX(Tracker!$I$9:$I$31,MATCH(G8,Tracker!$A$9:$A$31,0)),"")} -> In progress | I8: In progress | J8: =IFERROR(VLOOKUP(I8,Lists!$A$5:$B$8,2,FALSE()),0) -> 0.5
A9: US05 | B9: Accounts and access | C9: Company Admin | D9: As a Company Admin, I want an activity log of key actions, so that I can audit who changed what. | E9: Log shows user, action, target and time for employee, payroll and settings changes. | F9: Should | G9: T04 | H9: {=IFERROR(INDEX(Tracker!$I$9:$I$31,MATCH(G9,Tracker!$A$9:$A$31,0)),"")} -> In progress | I9: In progress | J9: =IFERROR(VLOOKUP(I9,Lists!$A$5:$B$8,2,FALSE()),0) -> 0.5
A10: US06 | B10: Company setup | C10: Company Admin | D10: As a Company Admin, I want to set company information and payroll settings, so that payroll follows our policy. | E10: Company details, pay frequency, rates and rules saved per company. | F10: Must | G10: T05 | H10: {=IFERROR(INDEX(Tracker!$I$9:$I$31,MATCH(G10,Tracker!$A$9:$A$31,0)),"")} -> In progress | I10: In progress | J10: =IFERROR(VLOOKUP(I10,Lists!$A$5:$B$8,2,FALSE()),0) -> 0.5
A11: US07 | B11: Company setup | C11: Company Admin | D11: As a Company Admin, I want to manage holidays, so that holiday pay is computed correctly. | E11: Add regular and special holidays; payroll reads them by date. | F11: Should | G11: T05 | H11: {=IFERROR(INDEX(Tracker!$I$9:$I$31,MATCH(G11,Tracker!$A$9:$A$31,0)),"")} -> In progress | I11: In progress | J11: =IFERROR(VLOOKUP(I11,Lists!$A$5:$B$8,2,FALSE()),0) -> 0.5
A12: US08 | B12: Company setup | C12: Company Admin | D12: As a Company Admin, I want to manage branches and follow an onboarding checklist, so that a new company is ready for payroll. | E12: Branch CRUD; checklist shows steps done and marks Ready for Payroll. | F12: Should | G12: T06 | H12: {=IFERROR(INDEX(Tracker!$I$9:$I$31,MATCH(G12,Tracker!$A$9:$A$31,0)),"")} -> In progress | I12: In progress | J12: =IFERROR(VLOOKUP(I12,Lists!$A$5:$B$8,2,FALSE()),0) -> 0.5
A13: US09 | B13: Employees | C13: HR Admin | D13: As an HR Admin, I want a searchable employee list, so that I can find any employee quickly. | E13: Search and filters by branch, status and department; data limited to own company. | F13: Must | G13: T07 | H13: {=IFERROR(INDEX(Tracker!$I$9:$I$31,MATCH(G13,Tracker!$A$9:$A$31,0)),"")} -> In progress | I13: In progress | J13: =IFERROR(VLOOKUP(I13,Lists!$A$5:$B$8,2,FALSE()),0) -> 0.5
A14: US10 | B14: Employees | C14: HR Admin | D14: As an HR Admin, I want to add and edit an employee profile, so that records stay accurate. | E14: Required fields validated; create and update are saved and written to the activity log. | F14: Must | G14: T07 | H14: {=IFERROR(INDEX(Tracker!$I$9:$I$31,MATCH(G14,Tracker!$A$9:$A$31,0)),"")} -> In progress | I14: In progress | J14: =IFERROR(VLOOKUP(I14,Lists!$A$5:$B$8,2,FALSE()),0) -> 0.5
A15: US11 | B15: Employees | C15: HR Admin | D15: As an HR Admin, I want to import employees from a file, so that I do not retype the whole roster. | E15: Import validates rows and reports errors before saving. | F15: Should | G15: T07 | H15: {=IFERROR(INDEX(Tracker!$I$9:$I$31,MATCH(G15,Tracker!$A$9:$A$31,0)),"")} -> In progress | I15: In progress | J15: =IFERROR(VLOOKUP(I15,Lists!$A$5:$B$8,2,FALSE()),0) -> 0.5
A16: US12 | B16: Employees | C16: Payroll Admin | D16: As a Payroll Admin, I want to set each employee's pay rate and compensation type, so that payroll computes the right amount. | E16: Monthly, daily, hourly and output-based rates supported; changes need permission. | F16: Must | G16: T07 | H16: {=IFERROR(INDEX(Tracker!$I$9:$I$31,MATCH(G16,Tracker!$A$9:$A$31,0)),"")} -> In progress | I16: In progress | J16: =IFERROR(VLOOKUP(I16,Lists!$A$5:$B$8,2,FALSE()),0) -> 0.5
... A50: US46 | B50: Quality and launch | C50: Project Owner | D50: As the Project Owner, I want UAT sign-off and a pilot with a real company, so that we launch only when it works. | E50: UAT scenarios run by real users; written sign-off before go-live. | F50: Must | G50: T23 | H50: {=IFERROR(INDEX(Tracker!$I$9:$I$31,MATCH(G50,Tracker!$A$9:$A$31,0)),"")} -> Not started | I50: Not started | J50: =IFERROR(VLOOKUP(I50,Lists!$A$5:$B$8,2,FALSE()),0) -> 0
A52: Priority: Must = needed for launch, Should = important, Could = nice to have (assumed by the author). Set each story's Status in column I (Progress % follows from it). Task status is shown for reference only.

Sheet Story Summary
A1: User story summary
A2: ="Project Owner: "&Tracker!$C$3&" | Counts and progress of the user stories (linked to the User Stories sheet)" -> Project Owner: Thea Consignado | Counts and progress of the user stories (linked to the User Stories sheet)
A4: Summary
A5: Total stories | B5: =COUNTA('User Stories'!$A$5:$A$50) -> 46
A6: Must have | B6: =COUNTIF('User Stories'!$F$5:$F$50,"Must") -> 31
A7: Should have | B7: =COUNTIF('User Stories'!$F$5:$F$50,"Should") -> 13
A8: Could have | B8: =COUNTIF('User Stories'!$F$5:$F$50,"Could") -> 2
A9: Stories done | B9: =COUNTIF('User Stories'!$I$5:$I$50,"Done") -> 0
A10: Average story progress | B10: =AVERAGE('User Stories'!$J$5:$J$50) -> 0.47826087
A13: Stories by module
A14: Module | B14: Stories | C14: Avg progress
A15: Accounts and access | B15: =COUNTIF('User Stories'!$B$5:$B$50,A15) -> 5 | C15: =IFERROR(SUMIFS('User Stories'!$J$5:$J$50,'User Stories'!$B$5:$B$50,A15)/B15,0) -> 0.5
A16: Company setup | B16: =COUNTIF('User Stories'!$B$5:$B$50,A16) -> 3 | C16: =IFERROR(SUMIFS('User Stories'!$J$5:$J$50,'User Stories'!$B$5:$B$50,A16)/B16,0) -> 0.5
A17: Employees | B17: =COUNTIF('User Stories'!$B$5:$B$50,A17) -> 4 | C17: =IFERROR(SUMIFS('User Stories'!$J$5:$J$50,'User Stories'!$B$5:$B$50,A17)/B17,0) -> 0.5
A18: Attendance and schedules | B18: =COUNTIF('User Stories'!$B$5:$B$50,A18) -> 5 | C18: =IFERROR(SUMIFS('User Stories'!$J$5:$J$50,'User Stories'!$B$5:$B$50,A18)/B18,0) -> 0.5
A19: Leave, overtime and approvals | B19: =COUNTIF('User Stories'!$B$5:$B$50,A19) -> 6 | C19: =IFERROR(SUMIFS('User Stories'!$J$5:$J$50,'User Stories'!$B$5:$B$50,A19)/B19,0) -> 0.5
A20: Loans, deductions and statutory | B20: =COUNTIF('User Stories'!$B$5:$B$50,A20) -> 5 | C20: =IFERROR(SUMIFS('User Stories'!$J$5:$J$50,'User Stories'!$B$5:$B$50,A20)/B20,0) -> 0.5
A21: Payroll and payslips | B21: =COUNTIF('User Stories'!$B$5:$B$50,A21) -> 5 | C21: =IFERROR(SUMIFS('User Stories'!$J$5:$J$50,'User Stories'!$B$5:$B$50,A21)/B21,0) -> 0.5
A22: Bonuses and 13th month | B22: =COUNTIF('User Stories'!$B$5:$B$50,A22) -> 2 | C22: =IFERROR(SUMIFS('User Stories'!$J$5:$J$50,'User Stories'!$B$5:$B$50,A22)/B22,0) -> 0.5
A23: Reports and dashboard | B23: =COUNTIF('User Stories'!$B$5:$B$50,A23) -> 3 | C23: =IFERROR(SUMIFS('User Stories'!$J$5:$J$50,'User Stories'!$B$5:$B$50,A23)/B23,0) -> 0.5
A24: Self-service portals | B24: =COUNTIF('User Stories'!$B$5:$B$50,A24) -> 3 | C24: =IFERROR(SUMIFS('User Stories'!$J$5:$J$50,'User Stories'!$B$5:$B$50,A24)/B24,0) -> 0.5
A25: Platform and integrations | B25: =COUNTIF('User Stories'!$B$5:$B$50,A25) -> 3 | C25: =IFERROR(SUMIFS('User Stories'!$J$5:$J$50,'User Stories'!$B$5:$B$50,A25)/B25,0) -> 0.5
A26: Quality and launch | B26: =COUNTIF('User Stories'!$B$5:$B$50,A26) -> 2 | C26: =IFERROR(SUMIFS('User Stories'!$J$5:$J$50,'User Stories'!$B$5:$B$50,A26)/B26,0) -> 0
A28: All figures are formulas linked to the User Stories sheet.

Sheet Lists
A1: Status list: what each status counts as
A2: ="Project Owner: "&Tracker!$C$3&" | Used by the Tracker and User Stories status dropdowns" -> Project Owner: Thea Consignado | Used by the Tracker and User Stories status dropdowns
A4: Status | B4: Counts as progress | C4: What it means
A5: Not started | B5: 0 | C5: Work has not begun
A6: In progress | B6: 0.5 | C6: Being built or written
A7: In testing | B7: 0.8 | C7: Built; being tested or reviewed
A8: Done | B8: 1 | C8: Finished and accepted
A10: Change the percentages (blue) if you want a different weighting. Keep Not started at 0% and Done at 100%. Do not rename the statuses: they feed the dropdowns, counts, and charts.

Sheet Plan calc
A1: Plan calculation (no inputs)
A2: ="Project Owner: "&Tracker!$C$3&" | Planned fraction of each task complete by the end of each week, assuming even effort across its weeks" -> Project Owner: Thea Consignado | Planned fraction of each task complete by the end of each week, assuming even effort across its weeks
A3: ID | B3: Task | C3: 0 | D3: 1 | E3: 2 | F3: 3 | G3: 4 | H3: 5 | I3: 6 | J3: 7 | K3: 8 | L3: 9 | M3: 10 | N3: 11 | O3: 12 | P3: 13
A4: =Tracker!A9 -> T01 | B4: =Tracker!C9 -> Project setup, architecture, UI/UX foundation | C4: =MAX(0,MIN(1,(C$3-Tracker!$D9+1)/(Tracker!$E9-Tracker!$D9+1))) -> 0 | D4: =MAX(0,MIN(1,(D$3-Tracker!$D9+1)/(Tracker!$E9-Tracker!$D9+1))) -> 1 | E4: =MAX(0,MIN(1,(E$3-Tracker!$D9+1)/(Tracker!$E9-Tracker!$D9+1))) -> 1 | F4: =MAX(0,MIN(1,(F$3-Tracker!$D9+1)/(Tracker!$E9-Tracker!$D9+1))) -> 1 | G4: =MAX(0,MIN(1,(G$3-Tracker!$D9+1)/(Tracker!$E9-Tracker!$D9+1))) -> 1 | H4: =MAX(0,MIN(1,(H$3-Tracker!$D9+1)/(Tracker!$E9-Tracker!$D9+1))) -> 1 | I4: =MAX(0,MIN(1,(I$3-Tracker!$D9+1)/(Tracker!$E9-Tracker!$D9+1))) -> 1 | J4: =MAX(0,MIN(1,(J$3-Tracker!$D9+1)/(Tracker!$E9-Tracker!$D9+1))) -> 1 | ... P4: =MAX(0,MIN(1,(P$3-Tracker!$D9+1)/(Tracker!$E9-Tracker!$D9+1))) -> 1
A5: =Tracker!A10 -> T02 | B5: =Tracker!C10 -> Database design and multi-tenant setup | C5: =MAX(0,MIN(1,(C$3-Tracker!$D10+1)/(Tracker!$E10-Tracker!$D10+1))) -> 0 | D5: =MAX(0,MIN(1,(D$3-Tracker!$D10+1)/(Tracker!$E10-Tracker!$D10+1))) -> 0.33333333 | E5: =MAX(0,MIN(1,(E$3-Tracker!$D10+1)/(Tracker!$E10-Tracker!$D10+1))) -> 0.66666667 | F5: =MAX(0,MIN(1,(F$3-Tracker!$D10+1)/(Tracker!$E10-Tracker!$D10+1))) -> 1 | G5: =MAX(0,MIN(1,(G$3-Tracker!$D10+1)/(Tracker!$E10-Tracker!$D10+1))) -> 1 | H5: =MAX(0,MIN(1,(H$3-Tracker!$D10+1)/(Tracker!$E10-Tracker!$D10+1))) -> 1 | I5: =MAX(0,MIN(1,(I$3-Tracker!$D10+1)/(Tracker!$E10-Tracker!$D10+1))) -> 1 | J5: =MAX(0,MIN(1,(J$3-Tracker!$D10+1)/(Tracker!$E10-Tracker!$D10+1))) -> 1 | ... P5: =MAX(0,MIN(1,(P$3-Tracker!$D10+1)/(Tracker!$E10-Tracker!$D10+1))) -> 1
A6: =Tracker!A11 -> T03 | B6: =Tracker!C11 -> Login, password reset, roles and permissions | C6: =MAX(0,MIN(1,(C$3-Tracker!$D11+1)/(Tracker!$E11-Tracker!$D11+1))) -> 0 | D6: =MAX(0,MIN(1,(D$3-Tracker!$D11+1)/(Tracker!$E11-Tracker!$D11+1))) -> 0.33333333 | E6: =MAX(0,MIN(1,(E$3-Tracker!$D11+1)/(Tracker!$E11-Tracker!$D11+1))) -> 0.66666667 | F6: =MAX(0,MIN(1,(F$3-Tracker!$D11+1)/(Tracker!$E11-Tracker!$D11+1))) -> 1 | G6: =MAX(0,MIN(1,(G$3-Tracker!$D11+1)/(Tracker!$E11-Tracker!$D11+1))) -> 1 | H6: =MAX(0,MIN(1,(H$3-Tracker!$D11+1)/(Tracker!$E11-Tracker!$D11+1))) -> 1 | I6: =MAX(0,MIN(1,(I$3-Tracker!$D11+1)/(Tracker!$E11-Tracker!$D11+1))) -> 1 | J6: =MAX(0,MIN(1,(J$3-Tracker!$D11+1)/(Tracker!$E11-Tracker!$D11+1))) -> 1 | ... P6: =MAX(0,MIN(1,(P$3-Tracker!$D11+1)/(Tracker!$E11-Tracker!$D11+1))) -> 1
A7: =Tracker!A12 -> T04 | B7: =Tracker!C12 -> User accounts, access and activity logs | C7: =MAX(0,MIN(1,(C$3-Tracker!$D12+1)/(Tracker!$E12-Tracker!$D12+1))) -> 0 | D7: =MAX(0,MIN(1,(D$3-Tracker!$D12+1)/(Tracker!$E12-Tracker!$D12+1))) -> 0 | E7: =MAX(0,MIN(1,(E$3-Tracker!$D12+1)/(Tracker!$E12-Tracker!$D12+1))) -> 0.5 | F7: =MAX(0,MIN(1,(F$3-Tracker!$D12+1)/(Tracker!$E12-Tracker!$D12+1))) -> 1 | G7: =MAX(0,MIN(1,(G$3-Tracker!$D12+1)/(Tracker!$E12-Tracker!$D12+1))) -> 1 | H7: =MAX(0,MIN(1,(H$3-Tracker!$D12+1)/(Tracker!$E12-Tracker!$D12+1))) -> 1 | I7: =MAX(0,MIN(1,(I$3-Tracker!$D12+1)/(Tracker!$E12-Tracker!$D12+1))) -> 1 | J7: =MAX(0,MIN(1,(J$3-Tracker!$D12+1)/(Tracker!$E12-Tracker!$D12+1))) -> 1 | ... P7: =MAX(0,MIN(1,(P$3-Tracker!$D12+1)/(Tracker!$E12-Tracker!$D12+1))) -> 1
A8: =Tracker!A13 -> T05 | B8: =Tracker!C13 -> Company information, payroll settings, holidays | C8: =MAX(0,MIN(1,(C$3-Tracker!$D13+1)/(Tracker!$E13-Tracker!$D13+1))) -> 0 | D8: =MAX(0,MIN(1,(D$3-Tracker!$D13+1)/(Tracker!$E13-Tracker!$D13+1))) -> 0 | E8: =MAX(0,MIN(1,(E$3-Tracker!$D13+1)/(Tracker!$E13-Tracker!$D13+1))) -> 0.5 | F8: =MAX(0,MIN(1,(F$3-Tracker!$D13+1)/(Tracker!$E13-Tracker!$D13+1))) -> 1 | G8: =MAX(0,MIN(1,(G$3-Tracker!$D13+1)/(Tracker!$E13-Tracker!$D13+1))) -> 1 | H8: =MAX(0,MIN(1,(H$3-Tracker!$D13+1)/(Tracker!$E13-Tracker!$D13+1))) -> 1 | I8: =MAX(0,MIN(1,(I$3-Tracker!$D13+1)/(Tracker!$E13-Tracker!$D13+1))) -> 1 | J8: =MAX(0,MIN(1,(J$3-Tracker!$D13+1)/(Tracker!$E13-Tracker!$D13+1))) -> 1 | ... P8: =MAX(0,MIN(1,(P$3-Tracker!$D13+1)/(Tracker!$E13-Tracker!$D13+1))) -> 1
A9: =Tracker!A14 -> T06 | B9: =Tracker!C14 -> Branches and onboarding | C9: =MAX(0,MIN(1,(C$3-Tracker!$D14+1)/(Tracker!$E14-Tracker!$D14+1))) -> 0 | D9: =MAX(0,MIN(1,(D$3-Tracker!$D14+1)/(Tracker!$E14-Tracker!$D14+1))) -> 0 | E9: =MAX(0,MIN(1,(E$3-Tracker!$D14+1)/(Tracker!$E14-Tracker!$D14+1))) -> 0 | F9: =MAX(0,MIN(1,(F$3-Tracker!$D14+1)/(Tracker!$E14-Tracker!$D14+1))) -> 1 | G9: =MAX(0,MIN(1,(G$3-Tracker!$D14+1)/(Tracker!$E14-Tracker!$D14+1))) -> 1 | H9: =MAX(0,MIN(1,(H$3-Tracker!$D14+1)/(Tracker!$E14-Tracker!$D14+1))) -> 1 | I9: =MAX(0,MIN(1,(I$3-Tracker!$D14+1)/(Tracker!$E14-Tracker!$D14+1))) -> 1 | J9: =MAX(0,MIN(1,(J$3-Tracker!$D14+1)/(Tracker!$E14-Tracker!$D14+1))) -> 1 | ... P9: =MAX(0,MIN(1,(P$3-Tracker!$D14+1)/(Tracker!$E14-Tracker!$D14+1))) -> 1
A10: =Tracker!A15 -> T07 | B10: =Tracker!C15 -> Employee management (list, profile, import) | C10: =MAX(0,MIN(1,(C$3-Tracker!$D15+1)/(Tracker!$E15-Tracker!$D15+1))) -> 0 | D10: =MAX(0,MIN(1,(D$3-Tracker!$D15+1)/(Tracker!$E15-Tracker!$D15+1))) -> 0 | E10: =MAX(0,MIN(1,(E$3-Tracker!$D15+1)/(Tracker!$E15-Tracker!$D15+1))) -> 0.5 | F10: =MAX(0,MIN(1,(F$3-Tracker!$D15+1)/(Tracker!$E15-Tracker!$D15+1))) -> 1 | G10: =MAX(0,MIN(1,(G$3-Tracker!$D15+1)/(Tracker!$E15-Tracker!$D15+1))) -> 1 | H10: =MAX(0,MIN(1,(H$3-Tracker!$D15+1)/(Tracker!$E15-Tracker!$D15+1))) -> 1 | I10: =MAX(0,MIN(1,(I$3-Tracker!$D15+1)/(Tracker!$E15-Tracker!$D15+1))) -> 1 | J10: =MAX(0,MIN(1,(J$3-Tracker!$D15+1)/(Tracker!$E15-Tracker!$D15+1))) -> 1 | ... P10: =MAX(0,MIN(1,(P$3-Tracker!$D15+1)/(Tracker!$E15-Tracker!$D15+1))) -> 1
A11: =Tracker!A16 -> T08 | B11: =Tracker!C16 -> Attendance, adjustments and biometrics | C11: =MAX(0,MIN(1,(C$3-Tracker!$D16+1)/(Tracker!$E16-Tracker!$D16+1))) -> 0 | D11: =MAX(0,MIN(1,(D$3-Tracker!$D16+1)/(Tracker!$E16-Tracker!$D16+1))) -> 0 | E11: =MAX(0,MIN(1,(E$3-Tracker!$D16+1)/(Tracker!$E16-Tracker!$D16+1))) -> 0 | F11: =MAX(0,MIN(1,(F$3-Tracker!$D16+1)/(Tracker!$E16-Tracker!$D16+1))) -> 0.5 | G11: =MAX(0,MIN(1,(G$3-Tracker!$D16+1)/(Tracker!$E16-Tracker!$D16+1))) -> 1 | H11: =MAX(0,MIN(1,(H$3-Tracker!$D16+1)/(Tracker!$E16-Tracker!$D16+1))) -> 1 | I11: =MAX(0,MIN(1,(I$3-Tracker!$D16+1)/(Tracker!$E16-Tracker!$D16+1))) -> 1 | J11: =MAX(0,MIN(1,(J$3-Tracker!$D16+1)/(Tracker!$E16-Tracker!$D16+1))) -> 1 | ... P11: =MAX(0,MIN(1,(P$3-Tracker!$D16+1)/(Tracker!$E16-Tracker!$D16+1))) -> 1
A12: =Tracker!A17 -> T09 | B12: =Tracker!C17 -> Schedules (roster, teams, shift templates) | C12: =MAX(0,MIN(1,(C$3-Tracker!$D17+1)/(Tracker!$E17-Tracker!$D17+1))) -> 0 | D12: =MAX(0,MIN(1,(D$3-Tracker!$D17+1)/(Tracker!$E17-Tracker!$D17+1))) -> 0 | E12: =MAX(0,MIN(1,(E$3-Tracker!$D17+1)/(Tracker!$E17-Tracker!$D17+1))) -> 0 | F12: =MAX(0,MIN(1,(F$3-Tracker!$D17+1)/(Tracker!$E17-Tracker!$D17+1))) -> 0.5 | G12: =MAX(0,MIN(1,(G$3-Tracker!$D17+1)/(Tracker!$E17-Tracker!$D17+1))) -> 1 | H12: =MAX(0,MIN(1,(H$3-Tracker!$D17+1)/(Tracker!$E17-Tracker!$D17+1))) -> 1 | I12: =MAX(0,MIN(1,(I$3-Tracker!$D17+1)/(Tracker!$E17-Tracker!$D17+1))) -> 1 | J12: =MAX(0,MIN(1,(J$3-Tracker!$D17+1)/(Tracker!$E17-Tracker!$D17+1))) -> 1 | ... P12: =MAX(0,MIN(1,(P$3-Tracker!$D17+1)/(Tracker!$E17-Tracker!$D17+1))) -> 1
A13: =Tracker!A18 -> T10 | B13: =Tracker!C18 -> Leave types, requests, approvals and balances | C13: =MAX(0,MIN(1,(C$3-Tracker!$D18+1)/(Tracker!$E18-Tracker!$D18+1))) -> 0 | D13: =MAX(0,MIN(1,(D$3-Tracker!$D18+1)/(Tracker!$E18-Tracker!$D18+1))) -> 0 | E13: =MAX(0,MIN(1,(E$3-Tracker!$D18+1)/(Tracker!$E18-Tracker!$D18+1))) -> 0 | F13: =MAX(0,MIN(1,(F$3-Tracker!$D18+1)/(Tracker!$E18-Tracker!$D18+1))) -> 0 | G13: =MAX(0,MIN(1,(G$3-Tracker!$D18+1)/(Tracker!$E18-Tracker!$D18+1))) -> 0.5 | H13: =MAX(0,MIN(1,(H$3-Tracker!$D18+1)/(Tracker!$E18-Tracker!$D18+1))) -> 1 | I13: =MAX(0,MIN(1,(I$3-Tracker!$D18+1)/(Tracker!$E18-Tracker!$D18+1))) -> 1 | J13: =MAX(0,MIN(1,(J$3-Tracker!$D18+1)/(Tracker!$E18-Tracker!$D18+1))) -> 1 | ... P13: =MAX(0,MIN(1,(P$3-Tracker!$D18+1)/(Tracker!$E18-Tracker!$D18+1))) -> 1
A14: =Tracker!A19 -> T11 | B14: =Tracker!C19 -> Overtime and night differential | C14: =MAX(0,MIN(1,(C$3-Tracker!$D19+1)/(Tracker!$E19-Tracker!$D19+1))) -> 0 | D14: =MAX(0,MIN(1,(D$3-Tracker!$D19+1)/(Tracker!$E19-Tracker!$D19+1))) -> 0 | E14: =MAX(0,MIN(1,(E$3-Tracker!$D19+1)/(Tracker!$E19-Tracker!$D19+1))) -> 0 | F14: =MAX(0,MIN(1,(F$3-Tracker!$D19+1)/(Tracker!$E19-Tracker!$D19+1))) -> 0 | G14: =MAX(0,MIN(1,(G$3-Tracker!$D19+1)/(Tracker!$E19-Tracker!$D19+1))) -> 0.5 | H14: =MAX(0,MIN(1,(H$3-Tracker!$D19+1)/(Tracker!$E19-Tracker!$D19+1))) -> 1 | I14: =MAX(0,MIN(1,(I$3-Tracker!$D19+1)/(Tracker!$E19-Tracker!$D19+1))) -> 1 | J14: =MAX(0,MIN(1,(J$3-Tracker!$D19+1)/(Tracker!$E19-Tracker!$D19+1))) -> 1 | ... P14: =MAX(0,MIN(1,(P$3-Tracker!$D19+1)/(Tracker!$E19-Tracker!$D19+1))) -> 1
A15: =Tracker!A20 -> T12 | B15: =Tracker!C20 -> Hourly and output compensation approvals | C15: =MAX(0,MIN(1,(C$3-Tracker!$D20+1)/(Tracker!$E20-Tracker!$D20+1))) -> 0 | D15: =MAX(0,MIN(1,(D$3-Tracker!$D20+1)/(Tracker!$E20-Tracker!$D20+1))) -> 0 | E15: =MAX(0,MIN(1,(E$3-Tracker!$D20+1)/(Tracker!$E20-Tracker!$D20+1))) -> 0 | F15: =MAX(0,MIN(1,(F$3-Tracker!$D20+1)/(Tracker!$E20-Tracker!$D20+1))) -> 0 | G15: =MAX(0,MIN(1,(G$3-Tracker!$D20+1)/(Tracker!$E20-Tracker!$D20+1))) -> 0 | H15: =MAX(0,MIN(1,(H$3-Tracker!$D20+1)/(Tracker!$E20-Tracker!$D20+1))) -> 0.5 | I15: =MAX(0,MIN(1,(I$3-Tracker!$D20+1)/(Tracker!$E20-Tracker!$D20+1))) -> 1 | J15: =MAX(0,MIN(1,(J$3-Tracker!$D20+1)/(Tracker!$E20-Tracker!$D20+1))) -> 1 | ... P15: =MAX(0,MIN(1,(P$3-Tracker!$D20+1)/(Tracker!$E20-Tracker!$D20+1))) -> 1
... A26: =Tracker!A31 -> T23 | B26: =Tracker!C31 -> UAT, pilot and go-live | C26: =MAX(0,MIN(1,(C$3-Tracker!$D31+1)/(Tracker!$E31-Tracker!$D31+1))) -> 0 | D26: =MAX(0,MIN(1,(D$3-Tracker!$D31+1)/(Tracker!$E31-Tracker!$D31+1))) -> 0 | E26: =MAX(0,MIN(1,(E$3-Tracker!$D31+1)/(Tracker!$E31-Tracker!$D31+1))) -> 0 | F26: =MAX(0,MIN(1,(F$3-Tracker!$D31+1)/(Tracker!$E31-Tracker!$D31+1))) -> 0 | G26: =MAX(0,MIN(1,(G$3-Tracker!$D31+1)/(Tracker!$E31-Tracker!$D31+1))) -> 0 | H26: =MAX(0,MIN(1,(H$3-Tracker!$D31+1)/(Tracker!$E31-Tracker!$D31+1))) -> 0 | I26: =MAX(0,MIN(1,(I$3-Tracker!$D31+1)/(Tracker!$E31-Tracker!$D31+1))) -> 0 | J26: =MAX(0,MIN(1,(J$3-Tracker!$D31+1)/(Tracker!$E31-Tracker!$D31+1))) -> 0 | ... P26: =MAX(0,MIN(1,(P$3-Tracker!$D31+1)/(Tracker!$E31-Tracker!$D31+1))) -> 1
